japanize_kivy/__init__.py
japanize_kivy/japanizer.py
japanize_kivy/resources/ipaexg00401/IPA_Font_License_Agreement_v1.0.txt
japanize_kivy/resources/ipaexg00401/Readme_ipaexg00401.txt
japanize_kivy/resources/ipaexg00401/ipaexg.ttf
japanize_kivy-0.1.1.dist-info/LICENSE
japanize_kivy-0.1.1.dist-info/METADATA
japanize_kivy-0.1.1.dist-info/WHEEL
japanize_kivy-0.1.1.dist-info/top_level.txt
japanize_kivy-0.1.1.dist-info/RECORD
